ClusterWrap/__init__.py
ClusterWrap/clusters.py
ClusterWrap/decorator.py
ClusterWrap-1.0.3.dist-info/LICENSE
ClusterWrap-1.0.3.dist-info/METADATA
ClusterWrap-1.0.3.dist-info/WHEEL
ClusterWrap-1.0.3.dist-info/top_level.txt
ClusterWrap-1.0.3.dist-info/RECORD
